<?xml version="1.0" encoding="UTF-8"?>
<objects serializationModel="Studio.02.02.00">
	<object class="AudioFile" id="{2b5c501c-7f94-426a-8f38-ef548884ba09}">
		<property name="assetPath">
			<value>DamageSound.wav</value>
		</property>
		<property name="frequencyInKHz">
			<value>44.0999985</value>
		</property>
		<property name="channelCount">
			<value>2</value>
		</property>
		<property name="length">
			<value>1.8509523809523809</value>
		</property>
		<relationship name="masterAssetFolder">
			<destination>{51d9d26e-5973-4851-8f66-d0c0696003f8}</destination>
		</relationship>
	</object>
</objects>
